<?xml version="1.0" encoding="UTF-8"?>
<metadata xml:lang="en"><Esri><CreaDate>20160728</CreaDate><CreaTime>11360800</CreaTime><ArcGISFormat>1.0</ArcGISFormat><SyncOnce>TRUE</SyncOnce><DataProperties><itemProps><itemLocation><linkage Sync="TRUE">file://\\FISH-CDW-086\SAU Backup\GIS\Primary_production\pprate</linkage><protocol Sync="TRUE">Local Area Network</protocol></itemLocation></itemProps><copyHistory><copy source="E:\Docs\Chris\Dirk_Projects3\Aylin_Mediterranean\Primary_Production\PP Data_World\pprate" dest="\\FISH-CDW-086\SAU Backup\GIS\Primary_production\pprate" date="20160728" time="11360800"></copy></copyHistory></DataProperties></Esri></metadata>
